<?xml version="1.0" encoding="UTF-8"?>
<verses title="Joshua 8" prevChapter="Joshua/Josh7.html" nextChapter="Joshua/Josh9.html">	<verse>
		<url>Joshua 8:1</url>
		<oref>Joshua 1:9</oref>
		<oref>Joshua 6:2</oref>
		<oref>Joshua 10:7</oref>
		<oref>Joshua 10:8</oref>
		<oref>Jeremiah 49:3</oref>
	</verse>
	<verse>
		<url>Joshua 8:2</url>
		<oref>Deuteronomy 20:14</oref>
	</verse>
	<verse>
		<url>Joshua 8:3</url>
	</verse>
	<verse>
		<url>Joshua 8:4</url>
		<oref>Judges 20:29</oref>
		<oref>2 Kings 7:12</oref>
		<oref>2 Chronicles 13:13</oref>
	</verse>
	<verse>
		<url>Joshua 8:5</url>
		<oref>Judges 20:32</oref>
	</verse>
	<verse>
		<url>Joshua 8:6</url>
	</verse>
	<verse>
		<url>Joshua 8:7</url>
		<oref>1 Samuel 23:4</oref>
	</verse>
	<verse>
		<url>Joshua 8:8</url>
		<oref>Deuteronomy 20:16</oref>
	</verse>
	<verse>
		<url>Joshua 8:9</url>
		<oref>Genesis 12:8</oref>
		<oref>1 Samuel 30:27</oref>
	</verse>
	<verse>
		<url>Joshua 8:10</url>
		<oref>Genesis 22:3</oref>
	</verse>
	<verse>
		<url>Joshua 8:11</url>
	</verse>
	<verse>
		<url>Joshua 8:12</url>
		<oref>Genesis 12:8</oref>
		<oref>Genesis 28:19</oref>
		<oref>Judges 1:22</oref>
	</verse>
	<verse>
		<url>Joshua 8:13</url>
	</verse>
	<verse>
		<url>Joshua 8:14</url>
		<oref>Judges 20:34</oref>
	</verse>
	<verse>
		<url>Joshua 8:15</url>
		<oref>Joshua 15:61</oref>
		<oref>Joshua 16:1</oref>
		<oref>Joshua 18:12</oref>
		<oref>Judges 20:36</oref>
		<oref>Judges 20:42</oref>
	</verse>
	<verse>
		<url>Joshua 8:16</url>
		<oref>Judges 20:31</oref>
	</verse>
	<verse>
		<url>Joshua 8:17</url>
	</verse>
	<verse>
		<url>Joshua 8:18</url>
		<oref>Exodus 14:16</oref>
		<oref>Exodus 17:9</oref>
		<oref>Ezekiel 30:25</oref>
	</verse>
	<verse>
		<url>Joshua 8:19</url>
		<oref>Judges 20:33</oref>
		<oref>Judges 20:37</oref>
	</verse>
	<verse>
		<url>Joshua 8:20</url>
		<oref>Judges 20:38</oref>
		<oref>Judges 20:40</oref>
	</verse>
	<verse>
		<url>Joshua 8:21</url>
		<oref>Joshua 10:1</oref>
	</verse>
	<verse>
		<url>Joshua 8:22</url>
	</verse>
	<verse>
		<url>Joshua 8:23</url>
	</verse>
	<verse>
		<url>Joshua 8:24</url>
		<oref>Judges 20:42</oref>
	</verse>
	<verse>
		<url>Joshua 8:25</url>
		<oref>Deuteronomy 20:16</oref>
	</verse>
	<verse>
		<url>Joshua 8:26</url>
		<oref>Exodus 17:11</oref>
		<oref>Exodus 17:12</oref>
	</verse>
	<verse>
		<url>Joshua 8:27</url>
	</verse>
	<verse>
		<url>Joshua 8:28</url>
		<oref>Deuteronomy 13:16</oref>
	</verse>
	<verse>
		<url>Joshua 8:29</url>
		<gref>John 19:31</gref>
		<oref>Deuteronomy 21:22</oref>
		<oref>Deuteronomy 21:23</oref>
		<oref>Joshua 10:26</oref>
		<oref>Joshua 12:9</oref>
		<oref>2 Samuel 18:17</oref>
	</verse>
	<verse>
		<url>Joshua 8:30</url>
		<oref>Deuteronomy 27:2</oref>
		<oref>Deuteronomy 27:4</oref>
	</verse>
	<verse>
		<url>Joshua 8:31</url>
		<oref>Exodus 20:25</oref>
		<oref>Deuteronomy 27:5</oref>
		<oref>Deuteronomy 27:6</oref>
	</verse>
	<verse>
		<url>Joshua 8:32</url>
		<oref>Deuteronomy 27:2</oref>
		<oref>Deuteronomy 27:3</oref>
	</verse>
	<verse>
		<url>Joshua 8:33</url>
		<gref>John 4:20</gref>
		<oref>Deuteronomy 11:29</oref>
		<oref>Deuteronomy 27:11</oref>
		<oref>Deuteronomy 27:12</oref>
	</verse>
	<verse>
		<url>Joshua 8:34</url>
		<oref>Deuteronomy 31:11</oref>
		<oref>Joshua 1:8</oref>
	</verse>
	<verse>
		<url>Joshua 8:35</url>
		<oref>Exodus 12:38</oref>
		<oref>Deuteronomy 31:12</oref>
		<oref>Zechariah 8:23</oref>
	</verse>
</verses>