<?xml version="1.0" encoding="UTF-8"?>
<verses title="Psalms 145" prevChapter="Psalms/Psa144.html" nextChapter="Psalms/Psa146.html">	<verse>
		<url>Psalms 145:1</url>
		<oref>Psalm 5:2</oref>
		<oref>Psalm 30:1</oref>
		<oref>Psalm 34:1</oref>
		<oref>Psalm 66:17</oref>
		<oref>Psalm 145:21</oref>
		<oref>Daniel 2:20</oref>
	</verse>
	<verse>
		<url>Psalms 145:2</url>
		<oref>Psalm 71:6</oref>
		<oref>Psalm 111:10</oref>
		<oref>Psalm 145:21</oref>
		<oref>Daniel 2:20</oref>
	</verse>
	<verse>
		<url>Psalms 145:3</url>
		<nref>Romans 11:33</nref>
		<oref>Job 5:9</oref>
		<oref>Job 9:10</oref>
		<oref>Job 11:7</oref>
		<oref>Psalm 18:3</oref>
		<oref>Psalm 48:1</oref>
		<oref>Psalm 86:10</oref>
		<oref>Psalm 95:3</oref>
		<oref>Psalm 96:4</oref>
		<oref>Psalm 135:5</oref>
		<oref>Psalm 147:5</oref>
		<oref>Psalm 150:2</oref>
		<oref>Isaiah 40:28</oref>
		<oref>Jeremiah 32:18</oref>
	</verse>
	<verse>
		<url>Psalms 145:4</url>
		<oref>Psalm 22:30</oref>
		<oref>Psalm 22:31</oref>
		<oref>Psalm 78:4</oref>
		<oref>Psalm 106:2</oref>
		<oref>Isaiah 12:4</oref>
		<oref>Isaiah 38:19</oref>
	</verse>
	<verse>
		<url>Psalms 145:5</url>
		<oref>Genesis 24:63</oref>
		<oref>Psalm 77:12</oref>
		<oref>Psalm 105:2</oref>
		<oref>Psalm 111:3</oref>
		<oref>Psalm 119:27</oref>
		<oref>Psalm 145:12</oref>
	</verse>
	<verse>
		<url>Psalms 145:6</url>
		<oref>Deuteronomy 10:21</oref>
		<oref>Deuteronomy 32:3</oref>
		<oref>Psalm 66:3</oref>
		<oref>Psalm 106:22</oref>
	</verse>
	<verse>
		<url>Psalms 145:7</url>
		<oref>Psalm 31:19</oref>
		<oref>Psalm 51:14</oref>
		<oref>Psalm 101:1</oref>
		<oref>Psalm 138:5</oref>
		<oref>Isaiah 63:7</oref>
	</verse>
	<verse>
		<url>Psalms 145:8</url>
		<oref>Exodus 34:6</oref>
		<oref>Numbers 14:18</oref>
		<oref>Psalm 86:5</oref>
		<oref>Psalm 86:15</oref>
		<oref>Psalm 103:8</oref>
		<oref>Psalm 111:4</oref>
	</verse>
	<verse>
		<url>Psalms 145:9</url>
		<gref>Matthew 19:17</gref>
		<gref>Mark 10:18</gref>
		<oref>Genesis 1:4</oref>
		<oref>Psalm 100:5</oref>
		<oref>Psalm 136:1</oref>
		<oref>Psalm 145:15</oref>
		<oref>Jeremiah 33:11</oref>
		<oref>Nahum 1:7</oref>
	</verse>
	<verse>
		<url>Psalms 145:10</url>
		<oref>Genesis 1:4</oref>
		<oref>Psalm 19:1</oref>
		<oref>Psalm 68:26</oref>
		<oref>Psalm 103:22</oref>
	</verse>
	<verse>
		<url>Psalms 145:11</url>
		<oref>Numbers 24:7</oref>
		<oref>Jeremiah 14:21</oref>
	</verse>
	<verse>
		<url>Psalms 145:12</url>
		<oref>Psalm 96:3</oref>
		<oref>Psalm 105:1</oref>
		<oref>Psalm 106:2</oref>
		<oref>Psalm 145:5</oref>
		<oref>Psalm 150:2</oref>
		<oref>Isaiah 2:10</oref>
		<oref>Isaiah 2:19</oref>
	</verse>
	<verse>
		<url>Psalms 145:13</url>
		<nref>1 Timothy 1:17</nref>
		<nref>2 Peter 1:11</nref>
		<oref>Psalm 10:16</oref>
		<oref>Psalm 29:10</oref>
		<oref>Psalm 66:7</oref>
		<oref>Daniel 2:44</oref>
		<oref>Daniel 4:34</oref>
		<oref>Daniel 7:27</oref>
	</verse>
	<verse>
		<url>Psalms 145:14</url>
		<oref>Psalm 37:17</oref>
		<oref>Psalm 37:24</oref>
		<oref>Psalm 54:4</oref>
		<oref>Psalm 57:6</oref>
		<oref>Psalm 146:8</oref>
	</verse>
	<verse>
		<url>Psalms 145:15</url>
		<oref>Genesis 1:30</oref>
		<oref>Psalm 104:21</oref>
		<oref>Psalm 104:27</oref>
		<oref>Psalm 136:25</oref>
		<oref>Psalm 145:9</oref>
		<oref>Psalm 146:7</oref>
		<oref>Psalm 147:9</oref>
	</verse>
	<verse>
		<url>Psalms 145:16</url>
		<oref>Genesis 1:30</oref>
		<oref>Psalm 36:6</oref>
		<oref>Psalm 103:5</oref>
		<oref>Psalm 104:28</oref>
	</verse>
	<verse>
		<url>Psalms 145:17</url>
		<oref>Exodus 9:27</oref>
		<oref>Psalm 18:30</oref>
		<oref>Psalm 116:5</oref>
		<oref>Psalm 119:137</oref>
	</verse>
	<verse>
		<url>Psalms 145:18</url>
		<gref>John 4:24</gref>
		<oref>Deuteronomy 4:7</oref>
		<oref>Psalm 34:18</oref>
		<oref>Psalm 46:1</oref>
		<oref>Psalm 75:1</oref>
		<oref>Psalm 119:151</oref>
		<oref>Proverbs 15:29</oref>
		<oref>Lamentations 3:57</oref>
		<oref>Daniel 9:20</oref>
	</verse>
	<verse>
		<url>Psalms 145:19</url>
		<gref>John 9:31</gref>
		<nref>1 John 5:14</nref>
		<oref>Psalm 10:17</oref>
		<oref>Psalm 20:4</oref>
		<oref>Psalm 21:2</oref>
		<oref>Psalm 31:22</oref>
		<oref>Psalm 34:17</oref>
		<oref>Psalm 37:4</oref>
		<oref>Proverbs 10:24</oref>
		<oref>Proverbs 15:29</oref>
		<oref>Isaiah 35:4</oref>
		<oref>Jeremiah 29:12</oref>
	</verse>
	<verse>
		<url>Psalms 145:20</url>
		<oref>1 Samuel 5:6</oref>
		<oref>1 Kings 3:3</oref>
		<oref>Psalm 9:5</oref>
		<oref>Psalm 31:23</oref>
		<oref>Psalm 37:38</oref>
		<oref>Psalm 91:14</oref>
		<oref>Psalm 97:10</oref>
	</verse>
	<verse>
		<url>Psalms 145:21</url>
		<oref>Psalm 65:2</oref>
		<oref>Psalm 71:8</oref>
		<oref>Psalm 103:1</oref>
		<oref>Psalm 113:2</oref>
		<oref>Psalm 145:1</oref>
		<oref>Psalm 145:2</oref>
		<oref>Psalm 150:6</oref>
	</verse>
</verses>