<?xml version="1.0" encoding="UTF-8"?>
<verses title="Job 33" prevChapter="Job/Job32.html" nextChapter="Job/Job34.html">	<verse>
		<url>Job 33:1</url>
		<oref>Job 13:6</oref>
		<oref>Job 32:22</oref>
	</verse>
	<verse>
		<url>Job 33:2</url>
	</verse>
	<verse>
		<url>Job 33:3</url>
		<oref>Job 6:28</oref>
		<oref>Job 27:4</oref>
		<oref>Job 36:4</oref>
	</verse>
	<verse>
		<url>Job 33:4</url>
		<oref>Genesis 2:7</oref>
		<oref>Job 10:3</oref>
		<oref>Job 10:12</oref>
		<oref>Job 12:10</oref>
		<oref>Job 27:3</oref>
		<oref>Job 32:8</oref>
		<oref>Psalm 104:30</oref>
		<oref>Isaiah 42:5</oref>
	</verse>
	<verse>
		<url>Job 33:5</url>
		<oref>Exodus 8:20</oref>
	</verse>
	<verse>
		<url>Job 33:6</url>
		<nref>2 Corinthians 4:7</nref>
		<oref>Job 4:19</oref>
		<oref>Job 10:9</oref>
	</verse>
	<verse>
		<url>Job 33:7</url>
		<oref>Job 13:21</oref>
		<oref>Psalm 32:4</oref>
	</verse>
	<verse>
		<url>Job 33:8</url>
	</verse>
	<verse>
		<url>Job 33:9</url>
		<oref>Job 7:21</oref>
		<oref>Job 9:21</oref>
		<oref>Job 10:7</oref>
		<oref>Job 10:14</oref>
		<oref>Job 13:18</oref>
		<oref>Job 13:23</oref>
		<oref>Job 14:17</oref>
		<oref>Job 16:17</oref>
		<oref>Job 34:5</oref>
	</verse>
	<verse>
		<url>Job 33:10</url>
		<oref>Job 13:24</oref>
		<oref>Job 16:9</oref>
		<oref>Job 19:11</oref>
	</verse>
	<verse>
		<url>Job 33:11</url>
		<nref>Acts 16:24</nref>
		<oref>Job 13:27</oref>
		<oref>Jeremiah 20:2</oref>
	</verse>
	<verse>
		<url>Job 33:12</url>
		<oref>Job 11:7</oref>
		<oref>Ecclesiastes 7:20</oref>
	</verse>
	<verse>
		<url>Job 33:13</url>
		<nref>Romans 9:20</nref>
		<oref>Job 11:7</oref>
		<oref>Job 40:2</oref>
		<oref>Isaiah 45:9</oref>
	</verse>
	<verse>
		<url>Job 33:14</url>
		<oref>Genesis 46:2</oref>
		<oref>Job 40:5</oref>
		<oref>Psalm 62:11</oref>
		<oref>Daniel 7:1</oref>
	</verse>
	<verse>
		<url>Job 33:15</url>
		<gref>Matthew 2:12</gref>
		<gref>Matthew 27:19</gref>
		<oref>Genesis 15:12</oref>
		<oref>Genesis 46:2</oref>
		<oref>Job 4:12</oref>
		<oref>Job 4:13</oref>
		<oref>Daniel 2:1</oref>
		<oref>Daniel 2:19</oref>
	</verse>
	<verse>
		<url>Job 33:16</url>
		<gref>Matthew 2:12</gref>
		<oref>Job 36:10</oref>
		<oref>Job 36:15</oref>
		<oref>Daniel 2:19</oref>
	</verse>
	<verse>
		<url>Job 33:17</url>
	</verse>
	<verse>
		<url>Job 33:18</url>
		<oref>Job 15:22</oref>
	</verse>
	<verse>
		<url>Job 33:19</url>
		<oref>Job 30:17</oref>
		<oref>Psalm 38:3</oref>
		<oref>Psalm 73:14</oref>
	</verse>
	<verse>
		<url>Job 33:20</url>
		<oref>Job 3:24</oref>
		<oref>Job 6:7</oref>
		<oref>Psalm 102:4</oref>
		<oref>Psalm 107:18</oref>
	</verse>
	<verse>
		<url>Job 33:21</url>
		<oref>Job 16:8</oref>
		<oref>Job 19:20</oref>
		<oref>Psalm 22:17</oref>
		<oref>Psalm 102:5</oref>
	</verse>
	<verse>
		<url>Job 33:22</url>
		<oref>Psalm 107:18</oref>
	</verse>
	<verse>
		<url>Job 33:23</url>
		<oref>Genesis 40:8</oref>
		<oref>Isaiah 59:16</oref>
	</verse>
	<verse>
		<url>Job 33:24</url>
		<oref>Job 36:18</oref>
		<oref>Psalm 49:7</oref>
		<oref>Isaiah 38:17</oref>
	</verse>
	<verse>
		<url>Job 33:25</url>
		<oref>2 Kings 5:14</oref>
	</verse>
	<verse>
		<url>Job 33:26</url>
		<oref>Job 22:26</oref>
		<oref>Job 22:27</oref>
		<oref>Job 34:28</oref>
		<oref>Psalm 18:20</oref>
		<oref>Psalm 50:14</oref>
		<oref>Psalm 50:15</oref>
	</verse>
	<verse>
		<url>Job 33:27</url>
		<gref>Luke 15:21</gref>
		<nref>Romans 6:21</nref>
		<oref>2 Samuel 12:13</oref>
		<oref>Job 34:32</oref>
	</verse>
	<verse>
		<url>Job 33:28</url>
		<oref>Job 22:28</oref>
		<oref>Psalm 107:20</oref>
		<oref>Jonah 2:6</oref>
	</verse>
	<verse>
		<url>Job 33:29</url>
		<nref>Ephesians 1:11</nref>
		<nref>Philippians 2:13</nref>
	</verse>
	<verse>
		<url>Job 33:30</url>
		<oref>Psalm 13:3</oref>
		<oref>Psalm 49:19</oref>
		<oref>Psalm 56:13</oref>
		<oref>Psalm 107:20</oref>
		<oref>Zechariah 9:11</oref>
	</verse>
	<verse>
		<url>Job 33:31</url>
		<oref>Jeremiah 23:18</oref>
	</verse>
	<verse>
		<url>Job 33:32</url>
	</verse>
	<verse>
		<url>Job 33:33</url>
		<oref>Job 34:1</oref>
		<oref>Psalm 34:11</oref>
	</verse>
</verses>