<?xml version="1.0" encoding="UTF-8"?>
<verses title="Matthew 11" prevChapter="Matthew/Matt10.html" nextChapter="Matthew/Matt12.html">	<verse>
		<url>Matthew 11:1</url>
		<gref>Matthew 7:28</gref>
		<gref>Matthew 9:35</gref>
		<gref>Mark 6:12</gref>
		<gref>Luke 23:5</gref>
	</verse>
	<verse>
		<url>Matthew 11:2</url>
		<gref>Matthew 4:12</gref>
		<gref>Matthew 14:3</gref>
		<gref>Mark 6:17</gref>
		<gref>Luke 7:18</gref>
		<gref>Luke 9:7</gref>
	</verse>
	<verse>
		<url>Matthew 11:3</url>
		<oref>Psalm 118:26</oref>
		<gref>John 6:14</gref>
		<gref>John 11:27</gref>
		<nref>Hebrews 10:37</nref>
	</verse>
	<verse>
		<url>Matthew 11:4</url>
		<gref>John 5:36</gref>
	</verse>
	<verse>
		<url>Matthew 11:5</url>
		<oref>Exodus 4:11</oref>
		<oref>Isaiah 29:18</oref>
		<oref>Isaiah 29:19</oref>
		<oref>Isaiah 35:5</oref>
		<oref>Isaiah 61:1</oref>
		<gref>Matthew 8:3</gref>
		<gref>Matthew 12:13</gref>
		<gref>Luke 4:18</gref>
		<gref>John 9:7</gref>
	</verse>
	<verse>
		<url>Matthew 11:6</url>
		<gref>Matthew 5:29</gref>
		<gref>Matthew 13:21</gref>
		<gref>Matthew 13:57</gref>
		<gref>Matthew 24:10</gref>
		<gref>Matthew 26:31</gref>
		<gref>Mark 6:3</gref>
		<gref>Luke 7:23</gref>
		<gref>John 6:61</gref>
		<gref>John 16:1</gref>
	</verse>
	<verse>
		<url>Matthew 11:7</url>
		<gref>Matthew 3:1</gref>
		<gref>Matthew 12:20</gref>
		<gref>Luke 7:24</gref>
	</verse>
	<verse>
		<url>Matthew 11:8</url>
		<oref>Deuteronomy 28:54</oref>
		<gref>Matthew 3:4</gref>
		<gref>Luke 7:25</gref>
	</verse>
	<verse>
		<url>Matthew 11:9</url>
		<gref>Matthew 14:5</gref>
		<gref>Matthew 21:26</gref>
		<gref>Luke 1:76</gref>
		<gref>Luke 20:6</gref>
	</verse>
	<verse>
		<url>Matthew 11:10</url>
		<oref>Malachi 3:1</oref>
		<gref>Mark 1:2</gref>
		<gref>Luke 1:76</gref>
		<gref>Luke 7:27</gref>
	</verse>
	<verse>
		<url>Matthew 11:11</url>
		<gref>Matthew 3:1</gref>
		<gref>Matthew 5:19</gref>
	</verse>
	<verse>
		<url>Matthew 11:12</url>
		<gref>Matthew 3:15</gref>
		<gref>Luke 16:16</gref>
	</verse>
	<verse>
		<url>Matthew 11:13</url>
	</verse>
	<verse>
		<url>Matthew 11:14</url>
		<oref>Malachi 3:1</oref>
		<oref>Malachi 4:5</oref>
		<gref>Matthew 17:10</gref>
		<gref>Mark 9:11</gref>
		<gref>Luke 1:17</gref>
		<gref>John 1:21</gref>
	</verse>
	<verse>
		<url>Matthew 11:15</url>
		<gref>Matthew 13:9</gref>
		<gref>Matthew 13:43</gref>
		<gref>Mark 4:9</gref>
		<gref>Mark 4:23</gref>
		<gref>Luke 8:8</gref>
		<gref>Luke 14:35</gref>
		<rref>Revelation 2:7</rref>
		<rref>Revelation 2:11</rref>
		<rref>Revelation 3:6</rref>
		<rref>Revelation 3:13</rref>
		<rref>Revelation 13:9</rref>
	</verse>
	<verse>
		<url>Matthew 11:16</url>
		<gref>Matthew 23:7</gref>
		<gref>Mark 12:38</gref>
		<gref>Luke 11:43</gref>
	</verse>
	<verse>
		<url>Matthew 11:17</url>
		<oref>Genesis 50:10</oref>
		<gref>Luke 7:32</gref>
		<gref>Luke 8:52</gref>
		<gref>Luke 23:27</gref>
	</verse>
	<verse>
		<url>Matthew 11:18</url>
		<gref>Matthew 3:4</gref>
		<gref>Matthew 9:34</gref>
		<gref>Mark 3:22</gref>
		<gref>Luke 1:15</gref>
		<gref>John 7:20</gref>
		<gref>John 8:48</gref>
		<gref>John 8:52</gref>
		<gref>John 10:20</gref>
	</verse>
	<verse>
		<url>Matthew 11:19</url>
		<oref>Proverbs 23:21</oref>
		<gref>Matthew 5:46</gref>
		<gref>Matthew 9:11</gref>
		<gref>Luke 5:29</gref>
		<gref>Luke 7:34</gref>
		<gref>Luke 15:2</gref>
	</verse>
	<verse>
		<url>Matthew 11:20</url>
		<gref>Luke 10:13</gref>
		<nref>2 Corinthians 12:21</nref>
	</verse>
	<verse>
		<url>Matthew 11:21</url>
		<oref>Joel 3:4</oref>
		<oref>Amos 1:9</oref>
		<gref>Matthew 15:21</gref>
		<gref>Mark 3:8</gref>
		<gref>Mark 6:45</gref>
		<gref>Mark 7:24</gref>
		<gref>Mark 7:31</gref>
		<gref>Mark 8:22</gref>
		<gref>Luke 4:26</gref>
		<gref>Luke 6:17</gref>
		<gref>Luke 9:10</gref>
		<gref>Luke 10:13</gref>
		<gref>Luke 10:14</gref>
		<gref>John 1:44</gref>
		<gref>John 12:21</gref>
		<nref>Acts 12:20</nref>
		<nref>Acts 27:3</nref>
		<rref>Revelation 6:12</rref>
		<rref>Revelation 11:3</rref>
	</verse>
	<verse>
		<url>Matthew 11:22</url>
		<oref>Joel 3:4</oref>
		<oref>Amos 1:9</oref>
		<gref>Matthew 10:15</gref>
		<gref>Matthew 12:36</gref>
		<rref>Revelation 20:11</rref>
		<rref>Revelation 20:12</rref>
	</verse>
	<verse>
		<url>Matthew 11:23</url>
		<oref>Isaiah 14:13</oref>
		<oref>Isaiah 14:15</oref>
		<oref>Ezekiel 16:48</oref>
		<oref>Ezekiel 26:20</oref>
		<oref>Ezekiel 31:14</oref>
		<oref>Ezekiel 32:18</oref>
		<oref>Ezekiel 32:24</oref>
		<gref>Matthew 4:13</gref>
		<gref>Matthew 10:15</gref>
		<gref>Matthew 16:18</gref>
		<gref>Luke 10:15</gref>
		<gref>Luke 16:23</gref>
		<nref>Acts 2:27</nref>
		<nref>Acts 2:31</nref>
		<nref>2 Peter 2:6</nref>
		<rref>Revelation 1:18</rref>
		<rref>Revelation 6:8</rref>
		<rref>Revelation 20:13</rref>
	</verse>
	<verse>
		<url>Matthew 11:24</url>
		<oref>Jeremiah 23:14</oref>
		<oref>Ezekiel 16:48</oref>
		<gref>Matthew 10:15</gref>
		<gref>Luke 10:12</gref>
	</verse>
	<verse>
		<url>Matthew 11:25</url>
		<oref>Job 37:24</oref>
		<oref>Psalm 8:2</oref>
		<gref>Matthew 21:16</gref>
		<gref>Luke 10:21</gref>
		<gref>Luke 10:22</gref>
		<gref>Luke 22:42</gref>
		<gref>Luke 23:34</gref>
		<gref>John 11:41</gref>
		<gref>John 12:27</gref>
		<gref>John 12:28</gref>
		<nref>Acts 17:24</nref>
		<nref>1 Corinthians 1:26</nref>
		<nref>1 Corinthians 2:10</nref>
	</verse>
	<verse>
		<url>Matthew 11:26</url>
		<gref>Luke 22:42</gref>
		<gref>Luke 23:34</gref>
		<gref>John 11:41</gref>
		<gref>John 12:27</gref>
		<gref>John 12:28</gref>
	</verse>
	<verse>
		<url>Matthew 11:27</url>
		<gref>Matthew 28:18</gref>
		<gref>Luke 10:22</gref>
		<gref>John 3:35</gref>
		<gref>John 7:29</gref>
		<gref>John 10:15</gref>
		<gref>John 13:3</gref>
		<gref>John 17:2</gref>
		<gref>John 17:25</gref>
		<nref>1 Corinthians 15:27</nref>
	</verse>
	<verse>
		<url>Matthew 11:28</url>
		<oref>Isaiah 28:12</oref>
		<oref>Jeremiah 31:25</oref>
		<gref>John 7:37</gref>
		<nref>Acts 20:35</nref>
	</verse>
	<verse>
		<url>Matthew 11:29</url>
		<oref>Numbers 12:3</oref>
		<oref>Psalm 116:7</oref>
		<oref>Proverbs 3:17</oref>
		<oref>Isaiah 28:12</oref>
		<oref>Isaiah 29:19</oref>
		<oref>Jeremiah 6:16</oref>
		<gref>John 13:15</gref>
		<nref>2 Corinthians 10:1</nref>
		<nref>Ephesians 4:20</nref>
		<nref>Philippians 2:5</nref>
		<nref>1 Peter 2:21</nref>
		<nref>1 John 2:6</nref>
	</verse>
	<verse>
		<url>Matthew 11:30</url>
		<nref>1 John 5:3</nref>
		<gref>Matthew 12:1</gref>
	</verse>
</verses>