<?xml version="1.0" encoding="UTF-8"?>
<verses title="1 Chronicles 10" prevChapter="1 Chronicles/1Chron9.html" nextChapter="1 Chronicles/1Chron11.html">	<verse>
		<url>1 Chronicles 10:1</url>
		<oref>1 Samuel 31:1</oref>
		<oref>1 Chronicles 9:44</oref>
	</verse>
	<verse>
		<url>1 Chronicles 10:2</url>
		<oref>1 Samuel 14:49</oref>
		<oref>1 Samuel 31:2</oref>
	</verse>
	<verse>
		<url>1 Chronicles 10:3</url>
	</verse>
	<verse>
		<url>1 Chronicles 10:4</url>
		<oref>Judges 9:54</oref>
		<oref>1 Samuel 31:4</oref>
		<oref>2 Samuel 1:6</oref>
	</verse>
	<verse>
		<url>1 Chronicles 10:5</url>
		<oref>Judges 9:54</oref>
	</verse>
	<verse>
		<url>1 Chronicles 10:6</url>
		<oref>1 Samuel 31:6</oref>
	</verse>
	<verse>
		<url>1 Chronicles 10:7</url>
	</verse>
	<verse>
		<url>1 Chronicles 10:8</url>
		<oref>1 Samuel 5:2</oref>
	</verse>
	<verse>
		<url>1 Chronicles 10:9</url>
		<oref>Judges 16:24</oref>
		<oref>1 Samuel 31:9</oref>
	</verse>
	<verse>
		<url>1 Chronicles 10:10</url>
	</verse>
	<verse>
		<url>1 Chronicles 10:11</url>
		<oref>Judges 21:8</oref>
	</verse>
	<verse>
		<url>1 Chronicles 10:12</url>
		<gref>John 11:19</gref>
		<oref>Genesis 12:6</oref>
		<oref>1 Samuel 31:12</oref>
	</verse>
	<verse>
		<url>1 Chronicles 10:13</url>
		<nref>Acts 16:16</nref>
		<oref>Leviticus 19:31</oref>
		<oref>Leviticus 20:6</oref>
		<oref>1 Samuel 13:13</oref>
		<oref>1 Samuel 13:14</oref>
		<oref>1 Samuel 15:23</oref>
		<oref>1 Samuel 28:6</oref>
		<oref>1 Samuel 28:7</oref>
		<oref>1 Samuel 28:8</oref>
		<oref>Isaiah 19:3</oref>
	</verse>
	<verse>
		<url>1 Chronicles 10:14</url>
		<oref>1 Samuel 15:28</oref>
		<oref>1 Samuel 28:6</oref>
		<oref>1 Chronicles 12:23</oref>
		<oref>1 Chronicles 17:13</oref>
	</verse>
</verses>