<?xml version="1.0" encoding="UTF-8"?>
<verses title="Ezekiel 37" prevChapter="Ezekiel/Eze36.html" nextChapter="Ezekiel/Eze38.html">	<verse>
		<url>Ezekiel 37:1</url>
		<nref>Acts 8:39</nref>
		<oref>Isaiah 26:19</oref>
		<oref>Jeremiah 7:2</oref>
		<oref>Ezekiel 1:3</oref>
		<oref>Ezekiel 8:3</oref>
		<oref>Ezekiel 11:24</oref>
		<oref>Ezekiel 33:22</oref>
		<oref>Ezekiel 40:1</oref>
		<oref>Ezekiel 43:5</oref>
	</verse>
	<verse>
		<url>Ezekiel 37:2</url>
	</verse>
	<verse>
		<url>Ezekiel 37:3</url>
		<nref>1 Corinthians 15:35</nref>
		<oref>Deuteronomy 32:39</oref>
		<oref>1 Samuel 2:6</oref>
		<oref>Ezekiel 26:19</oref>
	</verse>
	<verse>
		<url>Ezekiel 37:4</url>
		<rref>Revelation 10:11</rref>
		<oref>Jeremiah 22:29</oref>
		<oref>Ezekiel 36:1</oref>
	</verse>
	<verse>
		<url>Ezekiel 37:5</url>
		<rref>Revelation 11:11</rref>
		<oref>Genesis 2:7</oref>
		<oref>Psalm 104:29</oref>
		<oref>Psalm 104:30</oref>
	</verse>
	<verse>
		<url>Ezekiel 37:6</url>
		<oref>Exodus 6:3</oref>
		<oref>Isaiah 49:23</oref>
		<oref>Ezekiel 35:9</oref>
		<oref>Ezekiel 38:23</oref>
		<oref>Ezekiel 39:6</oref>
		<oref>Joel 2:27</oref>
		<oref>Joel 3:17</oref>
	</verse>
	<verse>
		<url>Ezekiel 37:7</url>
		<oref>Jeremiah 13:5</oref>
		<oref>Ezekiel 12:7</oref>
	</verse>
	<verse>
		<url>Ezekiel 37:8</url>
	</verse>
	<verse>
		<url>Ezekiel 37:9</url>
		<gref>John 3:8</gref>
		<rref>Revelation 10:11</rref>
		<rref>Revelation 11:11</rref>
		<oref>Psalm 104:30</oref>
		<oref>Daniel 11:4</oref>
		<oref>Hosea 13:14</oref>
		<oref>Zechariah 6:5</oref>
	</verse>
	<verse>
		<url>Ezekiel 37:10</url>
		<rref>Revelation 11:11</rref>
		<oref>Jeremiah 30:19</oref>
		<oref>Jeremiah 33:22</oref>
		<oref>Ezekiel 12:7</oref>
	</verse>
	<verse>
		<url>Ezekiel 37:11</url>
		<oref>Psalm 88:5</oref>
		<oref>Psalm 88:16</oref>
		<oref>Psalm 141:7</oref>
		<oref>Jeremiah 32:43</oref>
		<oref>Jeremiah 33:24</oref>
		<oref>Lamentations 3:18</oref>
		<oref>Lamentations 3:54</oref>
		<oref>Ezekiel 33:10</oref>
		<oref>Ezekiel 36:10</oref>
		<oref>Ezekiel 39:25</oref>
	</verse>
	<verse>
		<url>Ezekiel 37:12</url>
		<oref>Deuteronomy 32:39</oref>
		<oref>1 Samuel 2:6</oref>
		<oref>Isaiah 26:19</oref>
		<oref>Isaiah 66:14</oref>
		<oref>Daniel 12:2</oref>
		<oref>Hosea 13:14</oref>
		<oref>Zephaniah 3:20</oref>
	</verse>
	<verse>
		<url>Ezekiel 37:13</url>
		<oref>Exodus 6:3</oref>
		<oref>Hosea 13:14</oref>
	</verse>
	<verse>
		<url>Ezekiel 37:14</url>
		<oref>Isaiah 32:15</oref>
		<oref>Ezekiel 11:19</oref>
		<oref>Ezekiel 36:27</oref>
		<oref>Ezekiel 36:36</oref>
		<oref>Ezekiel 39:29</oref>
		<oref>Joel 2:28</oref>
		<oref>Joel 2:29</oref>
		<oref>Zechariah 12:10</oref>
	</verse>
	<verse>
		<url>Ezekiel 37:15</url>
	</verse>
	<verse>
		<url>Ezekiel 37:16</url>
		<oref>Numbers 17:2</oref>
		<oref>Numbers 17:3</oref>
		<oref>1 Kings 12:16</oref>
		<oref>2 Chronicles 10:17</oref>
		<oref>2 Chronicles 10:19</oref>
		<oref>2 Chronicles 11:11</oref>
		<oref>2 Chronicles 15:9</oref>
		<oref>Isaiah 11:13</oref>
		<oref>Zechariah 11:7</oref>
	</verse>
	<verse>
		<url>Ezekiel 37:17</url>
		<oref>Isaiah 11:13</oref>
		<oref>Jeremiah 50:4</oref>
		<oref>Hosea 1:11</oref>
		<oref>Zephaniah 3:9</oref>
	</verse>
	<verse>
		<url>Ezekiel 37:18</url>
		<oref>Ezekiel 12:9</oref>
		<oref>Ezekiel 17:12</oref>
		<oref>Ezekiel 20:49</oref>
		<oref>Ezekiel 24:19</oref>
		<oref>Ezekiel 33:2</oref>
	</verse>
	<verse>
		<url>Ezekiel 37:19</url>
	</verse>
	<verse>
		<url>Ezekiel 37:20</url>
	</verse>
	<verse>
		<url>Ezekiel 37:21</url>
		<oref>Isaiah 43:5</oref>
		<oref>Isaiah 43:6</oref>
		<oref>Jeremiah 29:14</oref>
		<oref>Ezekiel 36:10</oref>
		<oref>Ezekiel 36:24</oref>
		<oref>Ezekiel 38:8</oref>
		<oref>Ezekiel 39:25</oref>
		<oref>Ezekiel 39:27</oref>
		<oref>Hosea 1:11</oref>
		<oref>Amos 9:14</oref>
		<oref>Amos 9:15</oref>
		<oref>Micah 4:6</oref>
		<oref>Nahum 2:2</oref>
		<oref>Zephaniah 3:20</oref>
	</verse>
	<verse>
		<url>Ezekiel 37:22</url>
		<oref>Jeremiah 3:18</oref>
		<oref>Jeremiah 33:24</oref>
		<oref>Jeremiah 50:4</oref>
		<oref>Jeremiah 50:5</oref>
		<oref>Ezekiel 17:22</oref>
		<oref>Ezekiel 20:40</oref>
		<oref>Ezekiel 34:23</oref>
		<oref>Ezekiel 34:24</oref>
		<oref>Ezekiel 36:10</oref>
		<oref>Ezekiel 39:25</oref>
		<oref>Ezekiel 40:2</oref>
	</verse>
	<verse>
		<url>Ezekiel 37:23</url>
		<nref>Titus 2:14</nref>
		<oref>Ezekiel 11:18</oref>
		<oref>Ezekiel 14:11</oref>
		<oref>Ezekiel 36:25</oref>
		<oref>Ezekiel 36:28</oref>
		<oref>Ezekiel 36:29</oref>
	</verse>
	<verse>
		<url>Ezekiel 37:24</url>
		<gref>John 10:16</gref>
		<oref>Psalm 78:71</oref>
		<oref>Proverbs 9:6</oref>
		<oref>Isaiah 32:1</oref>
		<oref>Isaiah 40:11</oref>
		<oref>Isaiah 55:4</oref>
		<oref>Jeremiah 30:9</oref>
		<oref>Jeremiah 30:21</oref>
		<oref>Jeremiah 33:22</oref>
		<oref>Ezekiel 20:40</oref>
		<oref>Ezekiel 21:27</oref>
		<oref>Ezekiel 34:23</oref>
		<oref>Ezekiel 34:24</oref>
		<oref>Ezekiel 45:7</oref>
		<oref>Hosea 3:5</oref>
		<oref>Zechariah 13:7</oref>
	</verse>
	<verse>
		<url>Ezekiel 37:25</url>
		<gref>John 12:34</gref>
		<oref>Isaiah 11:1</oref>
		<oref>Isaiah 30:19</oref>
		<oref>Isaiah 55:4</oref>
		<oref>Jeremiah 30:9</oref>
		<oref>Jeremiah 32:39</oref>
		<oref>Ezekiel 34:24</oref>
		<oref>Ezekiel 44:3</oref>
		<oref>Daniel 2:44</oref>
		<oref>Joel 3:20</oref>
		<oref>Amos 9:15</oref>
		<oref>Zechariah 6:12</oref>
		<oref>Zechariah 8:8</oref>
		<oref>Zechariah 10:7</oref>
	</verse>
	<verse>
		<url>Ezekiel 37:26</url>
		<nref>Hebrews 13:20</nref>
		<oref>Leviticus 26:11</oref>
		<oref>Numbers 25:12</oref>
		<oref>Psalm 89:3</oref>
		<oref>Psalm 89:4</oref>
		<oref>Isaiah 55:3</oref>
		<oref>Isaiah 59:21</oref>
		<oref>Jeremiah 30:19</oref>
		<oref>Jeremiah 31:31</oref>
		<oref>Jeremiah 32:40</oref>
		<oref>Ezekiel 16:60</oref>
		<oref>Ezekiel 16:62</oref>
		<oref>Ezekiel 20:37</oref>
		<oref>Ezekiel 20:40</oref>
		<oref>Ezekiel 34:25</oref>
		<oref>Ezekiel 36:10</oref>
		<oref>Ezekiel 36:11</oref>
		<oref>Ezekiel 43:7</oref>
		<oref>Ezekiel 43:9</oref>
		<oref>Zephaniah 3:15</oref>
	</verse>
	<verse>
		<url>Ezekiel 37:27</url>
		<gref>John 1:14</gref>
		<nref>2 Corinthians 6:16</nref>
		<rref>Revelation 7:15</rref>
		<rref>Revelation 21:3</rref>
		<oref>Ezekiel 36:28</oref>
	</verse>
	<verse>
		<url>Ezekiel 37:28</url>
		<gref>Matthew 23:17</gref>
		<oref>Exodus 31:13</oref>
		<oref>Isaiah 30:19</oref>
		<oref>Ezekiel 20:12</oref>
		<oref>Ezekiel 38:1</oref>
		<oref>Ezekiel 38:23</oref>
		<oref>Ezekiel 43:7</oref>
	</verse>
</verses>