<?xml version="1.0" encoding="UTF-8"?>
<verses title="Ezekiel 9" prevChapter="Ezekiel/Eze8.html" nextChapter="Ezekiel/Eze10.html">	<verse>
		<url>Ezekiel 9:1</url>
		<oref>Isaiah 6:8</oref>
		<oref>Ezekiel 43:3</oref>
	</verse>
	<verse>
		<url>Ezekiel 9:2</url>
		<oref>Leviticus 16:4</oref>
		<oref>Daniel 10:5</oref>
		<oref>Daniel 12:6</oref>
	</verse>
	<verse>
		<url>Ezekiel 9:3</url>
		<oref>Ezekiel 10:4</oref>
		<oref>Ezekiel 11:22</oref>
		<oref>Ezekiel 11:23</oref>
	</verse>
	<verse>
		<url>Ezekiel 9:4</url>
		<nref>2 Corinthians 1:22</nref>
		<nref>Galatians 6:17</nref>
		<nref>2 Timothy 2:19</nref>
		<rref>Revelation 7:2</rref>
		<rref>Revelation 7:3</rref>
		<rref>Revelation 9:4</rref>
		<rref>Revelation 14:1</rref>
		<oref>Genesis 4:15</oref>
		<oref>Exodus 12:7</oref>
		<oref>Exodus 12:13</oref>
		<oref>Psalm 119:53</oref>
		<oref>Psalm 119:136</oref>
		<oref>Jeremiah 13:17</oref>
		<oref>Ezekiel 6:11</oref>
		<oref>Ezekiel 21:6</oref>
		<oref>Amos 6:6</oref>
		<oref>Zephaniah 1:12</oref>
		<oref>Zephaniah 3:18</oref>
	</verse>
	<verse>
		<url>Ezekiel 9:5</url>
		<oref>Isaiah 13:18</oref>
		<oref>Jeremiah 9:21</oref>
		<oref>Ezekiel 43:3</oref>
	</verse>
	<verse>
		<url>Ezekiel 9:6</url>
		<gref>Luke 12:47</gref>
		<nref>1 Peter 4:17</nref>
		<rref>Revelation 7:3</rref>
		<rref>Revelation 9:4</rref>
		<oref>Genesis 4:15</oref>
		<oref>Exodus 12:23</oref>
		<oref>2 Chronicles 36:17</oref>
		<oref>Jeremiah 9:21</oref>
		<oref>Jeremiah 16:6</oref>
		<oref>Jeremiah 25:29</oref>
		<oref>Amos 3:2</oref>
	</verse>
	<verse>
		<url>Ezekiel 9:7</url>
		<oref>2 Chronicles 36:17</oref>
		<oref>Ezekiel 7:20</oref>
	</verse>
	<verse>
		<url>Ezekiel 9:8</url>
		<oref>1 Chronicles 21:16</oref>
		<oref>Ezekiel 4:14</oref>
		<oref>Ezekiel 7:8</oref>
		<oref>Ezekiel 11:13</oref>
		<oref>Amos 7:2</oref>
	</verse>
	<verse>
		<url>Ezekiel 9:9</url>
		<oref>2 Kings 21:16</oref>
		<oref>Job 22:13</oref>
		<oref>Psalm 10:11</oref>
		<oref>Psalm 94:7</oref>
		<oref>Isaiah 29:15</oref>
		<oref>Isaiah 47:10</oref>
		<oref>Jeremiah 2:34</oref>
		<oref>Lamentations 1:5</oref>
		<oref>Ezekiel 7:23</oref>
		<oref>Ezekiel 8:12</oref>
		<oref>Ezekiel 8:17</oref>
		<oref>Ezekiel 22:2</oref>
		<oref>Ezekiel 22:3</oref>
		<oref>Ezekiel 22:29</oref>
		<oref>Micah 3:1</oref>
		<oref>Micah 7:3</oref>
		<oref>Habakkuk 1:4</oref>
		<oref>Zephaniah 1:12</oref>
	</verse>
	<verse>
		<url>Ezekiel 9:10</url>
		<oref>Isaiah 13:18</oref>
		<oref>Isaiah 65:6</oref>
		<oref>Lamentations 1:5</oref>
		<oref>Ezekiel 7:4</oref>
		<oref>Ezekiel 8:18</oref>
		<oref>Ezekiel 11:21</oref>
		<oref>Ezekiel 22:31</oref>
		<oref>Ezekiel 23:49</oref>
		<oref>Ezekiel 24:14</oref>
		<oref>Hosea 9:7</oref>
	</verse>
	<verse>
		<url>Ezekiel 9:11</url>
		<oref>Ezekiel 10:1</oref>
	</verse>
</verses>