<?xml version="1.0" encoding="UTF-8"?>
<verses title="Exodus 6" prevChapter="Exodus/Exo5.html" nextChapter="Exodus/Exo7.html">	<verse>
		<url>Exodus 6:1</url>
		<nref>Acts 13:17</nref>
		<oref>Exodus 3:19</oref>
		<oref>Exodus 3:20</oref>
		<oref>Exodus 7:4</oref>
		<oref>Exodus 7:5</oref>
		<oref>Exodus 11:1</oref>
		<oref>Exodus 12:31</oref>
		<oref>Exodus 12:33</oref>
		<oref>Exodus 12:39</oref>
		<oref>Exodus 13:3</oref>
		<oref>Exodus 15:6</oref>
		<oref>Psalm 136:12</oref>
	</verse>
	<verse>
		<url>Exodus 6:2</url>
		<oref>Exodus 3:14</oref>
		<oref>Exodus 3:15</oref>
		<oref>Exodus 12:12</oref>
		<oref>Exodus 15:3</oref>
		<oref>Ezekiel 20:5</oref>
	</verse>
	<verse>
		<url>Exodus 6:3</url>
		<oref>Genesis 17:1</oref>
		<oref>Genesis 35:11</oref>
		<oref>Genesis 48:3</oref>
		<oref>Exodus 3:14</oref>
		<oref>Exodus 15:3</oref>
		<oref>Exodus 23:21</oref>
		<oref>Ruth 1:20</oref>
		<oref>Psalm 68:4</oref>
		<oref>Psalm 83:18</oref>
		<oref>Isaiah 52:6</oref>
		<oref>Jeremiah 16:21</oref>
		<oref>Jeremiah 33:2</oref>
		<oref>Ezekiel 20:5</oref>
		<oref>Ezekiel 37:6</oref>
		<oref>Ezekiel 37:13</oref>
	</verse>
	<verse>
		<url>Exodus 6:4</url>
		<oref>Genesis 12:7</oref>
		<oref>Genesis 15:18</oref>
		<oref>Genesis 17:4</oref>
		<oref>Genesis 17:7</oref>
		<oref>Genesis 26:3</oref>
		<oref>Genesis 26:4</oref>
		<oref>Genesis 28:4</oref>
		<oref>Genesis 28:13</oref>
		<oref>Numbers 10:29</oref>
	</verse>
	<verse>
		<url>Exodus 6:5</url>
		<oref>Exodus 2:23</oref>
		<oref>Exodus 2:24</oref>
		<oref>Exodus 5:4</oref>
	</verse>
	<verse>
		<url>Exodus 6:6</url>
		<nref>Acts 13:17</nref>
		<oref>Exodus 1:11</oref>
		<oref>Exodus 2:11</oref>
		<oref>Exodus 12:41</oref>
		<oref>Exodus 12:51</oref>
		<oref>Exodus 13:3</oref>
		<oref>Exodus 13:14</oref>
		<oref>Exodus 15:13</oref>
		<oref>Exodus 16:6</oref>
		<oref>Exodus 18:1</oref>
		<oref>Deuteronomy 4:34</oref>
		<oref>Deuteronomy 5:15</oref>
		<oref>Deuteronomy 6:12</oref>
		<oref>Deuteronomy 7:8</oref>
		<oref>Deuteronomy 26:8</oref>
		<oref>2 Kings 17:36</oref>
		<oref>1 Chronicles 17:21</oref>
		<oref>Psalm 136:12</oref>
		<oref>Jeremiah 21:5</oref>
		<oref>Jeremiah 32:21</oref>
	</verse>
	<verse>
		<url>Exodus 6:7</url>
		<oref>Genesis 17:7</oref>
		<oref>Genesis 17:8</oref>
		<oref>Exodus 2:11</oref>
		<oref>Exodus 16:6</oref>
		<oref>Exodus 16:12</oref>
		<oref>Exodus 19:5</oref>
		<oref>Exodus 29:45</oref>
		<oref>Leviticus 11:44</oref>
		<oref>Leviticus 11:45</oref>
		<oref>Deuteronomy 4:20</oref>
		<oref>Deuteronomy 7:6</oref>
		<oref>Deuteronomy 26:18</oref>
		<oref>Deuteronomy 29:13</oref>
		<oref>Isaiah 41:20</oref>
		<oref>Isaiah 49:23</oref>
		<oref>Isaiah 49:26</oref>
		<oref>Isaiah 60:16</oref>
		<oref>Isaiah 63:8</oref>
		<oref>Jeremiah 30:22</oref>
		<oref>Ezekiel 20:19</oref>
	</verse>
	<verse>
		<url>Exodus 6:8</url>
		<rref>Revelation 10:6</rref>
		<oref>Genesis 15:18</oref>
		<oref>Genesis 26:3</oref>
		<oref>Exodus 13:5</oref>
		<oref>Numbers 14:30</oref>
		<oref>Joshua 24:13</oref>
		<oref>Nehemiah 9:15</oref>
		<oref>Psalm 136:21</oref>
		<oref>Psalm 136:22</oref>
		<oref>Ezekiel 20:5</oref>
		<oref>Ezekiel 20:6</oref>
	</verse>
	<verse>
		<url>Exodus 6:9</url>
		<oref>Exodus 1:14</oref>
		<oref>Exodus 2:23</oref>
		<oref>Exodus 14:12</oref>
	</verse>
	<verse>
		<url>Exodus 6:10</url>
	</verse>
	<verse>
		<url>Exodus 6:11</url>
		<oref>Exodus 4:22</oref>
		<oref>Exodus 4:23</oref>
		<oref>Exodus 5:1</oref>
	</verse>
	<verse>
		<url>Exodus 6:12</url>
		<oref>Exodus 3:11</oref>
		<oref>Exodus 4:1</oref>
		<oref>Exodus 4:10</oref>
		<oref>Isaiah 6:5</oref>
		<oref>Jeremiah 1:6</oref>
	</verse>
	<verse>
		<url>Exodus 6:13</url>
	</verse>
	<verse>
		<url>Exodus 6:14</url>
		<oref>Genesis 46:9</oref>
		<oref>Numbers 26:5</oref>
		<oref>1 Chronicles 5:3</oref>
	</verse>
	<verse>
		<url>Exodus 6:15</url>
		<oref>Genesis 46:10</oref>
		<oref>1 Chronicles 4:24</oref>
	</verse>
	<verse>
		<url>Exodus 6:16</url>
		<oref>Genesis 46:11</oref>
		<oref>Exodus 2:1</oref>
		<oref>Numbers 3:17</oref>
		<oref>Numbers 26:57</oref>
		<oref>1 Chronicles 6:1</oref>
		<oref>1 Chronicles 6:16</oref>
	</verse>
	<verse>
		<url>Exodus 6:17</url>
		<oref>Numbers 3:18</oref>
		<oref>1 Chronicles 6:17</oref>
		<oref>1 Chronicles 6:29</oref>
	</verse>
	<verse>
		<url>Exodus 6:18</url>
		<oref>Exodus 2:1</oref>
		<oref>Numbers 3:19</oref>
		<oref>1 Chronicles 6:2</oref>
		<oref>1 Chronicles 6:18</oref>
		<oref>1 Chronicles 23:12</oref>
	</verse>
	<verse>
		<url>Exodus 6:19</url>
		<oref>Numbers 3:20</oref>
		<oref>1 Chronicles 6:19</oref>
		<oref>1 Chronicles 23:21</oref>
		<oref>1 Chronicles 23:23</oref>
	</verse>
	<verse>
		<url>Exodus 6:20</url>
		<oref>Exodus 2:1</oref>
		<oref>Exodus 2:2</oref>
		<oref>Numbers 3:1</oref>
		<oref>Numbers 26:58</oref>
		<oref>Numbers 26:59</oref>
		<oref>1 Chronicles 23:13</oref>
	</verse>
	<verse>
		<url>Exodus 6:21</url>
		<oref>Numbers 16:1</oref>
		<oref>1 Chronicles 6:37</oref>
		<oref>1 Chronicles 6:38</oref>
		<oref>2 Chronicles 17:16</oref>
	</verse>
	<verse>
		<url>Exodus 6:22</url>
		<oref>Leviticus 10:4</oref>
		<oref>Numbers 3:30</oref>
	</verse>
	<verse>
		<url>Exodus 6:23</url>
		<oref>Exodus 24:1</oref>
		<oref>Leviticus 10:1</oref>
		<oref>Leviticus 10:12</oref>
		<oref>Numbers 1:7</oref>
		<oref>Numbers 2:3</oref>
		<oref>Numbers 3:2</oref>
		<oref>Numbers 26:60</oref>
		<oref>Ruth 4:19</oref>
		<oref>Ruth 4:20</oref>
		<oref>1 Chronicles 2:10</oref>
		<oref>1 Chronicles 6:3</oref>
		<oref>1 Chronicles 24:1</oref>
	</verse>
	<verse>
		<url>Exodus 6:24</url>
		<oref>Numbers 26:11</oref>
		<oref>1 Chronicles 6:22</oref>
		<oref>1 Chronicles 6:23</oref>
		<oref>1 Chronicles 12:6</oref>
	</verse>
	<verse>
		<url>Exodus 6:25</url>
		<oref>Numbers 25:7</oref>
		<oref>Joshua 24:33</oref>
		<oref>Psalm 106:30</oref>
	</verse>
	<verse>
		<url>Exodus 6:26</url>
		<oref>Exodus 3:10</oref>
		<oref>Exodus 7:4</oref>
		<oref>Exodus 12:17</oref>
		<oref>Exodus 12:51</oref>
		<oref>1 Samuel 12:6</oref>
		<oref>Psalm 77:20</oref>
	</verse>
	<verse>
		<url>Exodus 6:27</url>
		<oref>Exodus 5:1</oref>
	</verse>
	<verse>
		<url>Exodus 6:28</url>
	</verse>
	<verse>
		<url>Exodus 6:29</url>
		<oref>Exodus 7:2</oref>
	</verse>
	<verse>
		<url>Exodus 6:30</url>
		<oref>Exodus 4:1</oref>
		<oref>Exodus 4:10</oref>
		<oref>Isaiah 6:5</oref>
		<oref>Jeremiah 1:6</oref>
	</verse>
</verses>