<?xml version="1.0" encoding="UTF-8"?>
<verses title="Ecclesiastes 6" prevChapter="Ecclesiastes/Ecc5.html" nextChapter="Ecclesiastes/Ecc7.html">	<verse>
		<url>Ecclesiastes 6:1</url>
		<oref>Ecclesiastes 5:13</oref>
	</verse>
	<verse>
		<url>Ecclesiastes 6:2</url>
		<oref>1 Kings 3:13</oref>
		<oref>Psalm 17:14</oref>
		<oref>Psalm 73:7</oref>
		<oref>Ecclesiastes 2:10</oref>
		<oref>Ecclesiastes 5:13</oref>
		<oref>Ecclesiastes 5:19</oref>
		<oref>Isaiah 55:2</oref>
	</verse>
	<verse>
		<url>Ecclesiastes 6:3</url>
		<oref>Job 3:16</oref>
		<oref>Psalm 58:8</oref>
		<oref>Ecclesiastes 4:3</oref>
		<oref>Isaiah 14:20</oref>
		<oref>Jeremiah 8:2</oref>
		<oref>Jeremiah 22:19</oref>
	</verse>
	<verse>
		<url>Ecclesiastes 6:4</url>
	</verse>
	<verse>
		<url>Ecclesiastes 6:5</url>
		<oref>Ecclesiastes 11:7</oref>
	</verse>
	<verse>
		<url>Ecclesiastes 6:6</url>
		<oref>Ecclesiastes 2:14</oref>
		<oref>Ecclesiastes 7:2</oref>
		<oref>Ecclesiastes 9:2</oref>
	</verse>
	<verse>
		<url>Ecclesiastes 6:7</url>
		<oref>Proverbs 16:26</oref>
	</verse>
	<verse>
		<url>Ecclesiastes 6:8</url>
		<oref>Ecclesiastes 2:15</oref>
	</verse>
	<verse>
		<url>Ecclesiastes 6:9</url>
		<oref>Ecclesiastes 1:14</oref>
		<oref>Ecclesiastes 1:17</oref>
		<oref>Ecclesiastes 11:9</oref>
	</verse>
	<verse>
		<url>Ecclesiastes 6:10</url>
		<nref>1 Corinthians 10:22</nref>
		<oref>Job 9:32</oref>
		<oref>Job 40:2</oref>
		<oref>Proverbs 21:30</oref>
		<oref>Ecclesiastes 1:9</oref>
		<oref>Ecclesiastes 3:15</oref>
		<oref>Isaiah 45:9</oref>
	</verse>
	<verse>
		<url>Ecclesiastes 6:11</url>
		<oref>Ecclesiastes 2:15</oref>
	</verse>
	<verse>
		<url>Ecclesiastes 6:12</url>
		<oref>Psalm 39:5</oref>
		<oref>Ecclesiastes 2:3</oref>
		<oref>Ecclesiastes 2:24</oref>
		<oref>Ecclesiastes 3:22</oref>
		<oref>Ecclesiastes 7:15</oref>
		<oref>Ecclesiastes 8:7</oref>
		<oref>Ecclesiastes 8:13</oref>
		<oref>Ecclesiastes 9:9</oref>
		<oref>Ecclesiastes 10:14</oref>
	</verse>
</verses>