<?xml version="1.0" encoding="UTF-8"?>
<verses title="Isaiah 62" prevChapter="Isaiah/Isaiah61.html" nextChapter="Isaiah/Isaiah63.html">	<verse>
		<url>Isaiah 62:1</url>
		<oref>Isaiah 1:26</oref>
		<oref>Isaiah 26:2</oref>
		<oref>Isaiah 46:13</oref>
		<oref>Isaiah 48:18</oref>
		<oref>Isaiah 52:10</oref>
		<oref>Isaiah 54:14</oref>
		<oref>Isaiah 58:8</oref>
		<oref>Isaiah 61:11</oref>
	</verse>
	<verse>
		<url>Isaiah 62:2</url>
		<rref>Revelation 2:17</rref>
		<rref>Revelation 3:12</rref>
		<oref>Psalm 98:2</oref>
		<oref>Isaiah 1:26</oref>
		<oref>Isaiah 26:2</oref>
		<oref>Isaiah 43:7</oref>
		<oref>Isaiah 56:5</oref>
		<oref>Isaiah 60:3</oref>
		<oref>Isaiah 65:15</oref>
		<oref>Isaiah 66:11</oref>
		<oref>Jeremiah 33:9</oref>
	</verse>
	<verse>
		<url>Isaiah 62:3</url>
		<nref>1 Thessalonians 2:19</nref>
		<oref>Isaiah 28:5</oref>
		<oref>Zechariah 9:16</oref>
	</verse>
	<verse>
		<url>Isaiah 62:4</url>
		<oref>Isaiah 54:1</oref>
		<oref>Isaiah 54:6</oref>
		<oref>Isaiah 54:7</oref>
		<oref>Isaiah 60:15</oref>
		<oref>Isaiah 60:18</oref>
		<oref>Isaiah 65:19</oref>
		<oref>Jeremiah 32:41</oref>
		<oref>Jeremiah 33:9</oref>
		<oref>Hosea 2:19</oref>
		<oref>Hosea 2:20</oref>
		<oref>Zephaniah 3:17</oref>
		<oref>Malachi 3:12</oref>
	</verse>
	<verse>
		<url>Isaiah 62:5</url>
		<oref>Song of Solomon 3:11</oref>
		<oref>Song of Solomon 4:8</oref>
		<oref>Isaiah 65:19</oref>
		<oref>Jeremiah 32:41</oref>
		<oref>Hosea 2:19</oref>
		<oref>Zephaniah 3:17</oref>
	</verse>
	<verse>
		<url>Isaiah 62:6</url>
		<nref>Hebrews 13:17</nref>
		<oref>Psalm 74:2</oref>
		<oref>Psalm 122:7</oref>
		<oref>Isaiah 49:16</oref>
		<oref>Isaiah 52:8</oref>
		<oref>Jeremiah 6:17</oref>
		<oref>Jeremiah 14:21</oref>
		<oref>Lamentations 5:1</oref>
		<oref>Lamentations 5:20</oref>
		<oref>Ezekiel 3:17</oref>
		<oref>Ezekiel 33:7</oref>
	</verse>
	<verse>
		<url>Isaiah 62:7</url>
		<gref>Luke 18:1</gref>
		<oref>Isaiah 49:16</oref>
		<oref>Isaiah 60:18</oref>
		<oref>Jeremiah 33:9</oref>
		<oref>Zephaniah 3:19</oref>
		<oref>Zephaniah 3:20</oref>
	</verse>
	<verse>
		<url>Isaiah 62:8</url>
		<oref>Leviticus 26:16</oref>
		<oref>Deuteronomy 28:31</oref>
		<oref>Deuteronomy 28:33</oref>
		<oref>Judges 6:3</oref>
		<oref>Isaiah 1:7</oref>
		<oref>Isaiah 45:23</oref>
		<oref>Isaiah 54:9</oref>
		<oref>Isaiah 55:2</oref>
		<oref>Isaiah 65:22</oref>
		<oref>Jeremiah 5:17</oref>
	</verse>
	<verse>
		<url>Isaiah 62:9</url>
		<oref>Isaiah 55:2</oref>
		<oref>Isaiah 65:13</oref>
		<oref>Isaiah 65:21</oref>
		<oref>Isaiah 65:22</oref>
		<oref>Ezekiel 40:14</oref>
		<oref>Joel 2:26</oref>
		<oref>Zechariah 3:7</oref>
	</verse>
	<verse>
		<url>Isaiah 62:10</url>
		<oref>Psalm 68:4</oref>
		<oref>Isaiah 11:10</oref>
		<oref>Isaiah 11:12</oref>
		<oref>Isaiah 11:16</oref>
		<oref>Isaiah 19:23</oref>
		<oref>Isaiah 26:1</oref>
		<oref>Isaiah 26:2</oref>
		<oref>Isaiah 35:8</oref>
		<oref>Isaiah 49:11</oref>
		<oref>Isaiah 49:22</oref>
		<oref>Isaiah 57:14</oref>
		<oref>Isaiah 60:11</oref>
		<oref>Isaiah 60:18</oref>
		<oref>Isaiah 66:19</oref>
		<oref>Jeremiah 4:6</oref>
		<oref>Jeremiah 18:15</oref>
		<oref>Ezekiel 26:2</oref>
	</verse>
	<verse>
		<url>Isaiah 62:11</url>
		<gref>Matthew 21:5</gref>
		<rref>Revelation 22:12</rref>
		<oref>Deuteronomy 30:4</oref>
		<oref>Isaiah 12:2</oref>
		<oref>Isaiah 17:10</oref>
		<oref>Isaiah 40:10</oref>
		<oref>Isaiah 42:10</oref>
		<oref>Isaiah 46:13</oref>
		<oref>Isaiah 48:20</oref>
		<oref>Isaiah 49:6</oref>
		<oref>Isaiah 51:5</oref>
		<oref>Zechariah 9:9</oref>
	</verse>
	<verse>
		<url>Isaiah 62:12</url>
		<nref>1 Peter 2:9</nref>
		<oref>Exodus 19:6</oref>
		<oref>Deuteronomy 7:6</oref>
		<oref>Deuteronomy 26:19</oref>
		<oref>Psalm 107:2</oref>
		<oref>Isaiah 1:27</oref>
		<oref>Isaiah 4:3</oref>
		<oref>Isaiah 35:9</oref>
		<oref>Isaiah 41:17</oref>
		<oref>Isaiah 42:16</oref>
		<oref>Isaiah 51:10</oref>
		<oref>Isaiah 52:3</oref>
	</verse>
</verses>