<?xml version="1.0" encoding="UTF-8"?>
<verses title="Isaiah 4" prevChapter="Isaiah/Isaiah3.html" nextChapter="Isaiah/Isaiah5.html">	<verse>
		<url>Isaiah 4:1</url>
		<gref>Luke 1:25</gref>
		<oref>Genesis 30:23</oref>
		<oref>Isaiah 3:6</oref>
		<oref>Isaiah 13:12</oref>
		<oref>Isaiah 54:4</oref>
		<oref>Jeremiah 15:8</oref>
	</verse>
	<verse>
		<url>Isaiah 4:2</url>
		<oref>Psalm 72:16</oref>
		<oref>Isaiah 10:20</oref>
		<oref>Isaiah 11:1</oref>
		<oref>Isaiah 26:1</oref>
		<oref>Isaiah 27:6</oref>
		<oref>Isaiah 37:31</oref>
		<oref>Isaiah 37:32</oref>
		<oref>Isaiah 53:2</oref>
		<oref>Isaiah 60:15</oref>
		<oref>Isaiah 61:11</oref>
		<oref>Jeremiah 23:5</oref>
		<oref>Jeremiah 33:15</oref>
		<oref>Jeremiah 44:14</oref>
		<oref>Ezekiel 34:29</oref>
		<oref>Ezekiel 36:8</oref>
		<oref>Joel 2:32</oref>
		<oref>Obadiah 1:17</oref>
		<oref>Zechariah 3:8</oref>
		<oref>Zechariah 6:12</oref>
		<oref>Malachi 3:17</oref>
	</verse>
	<verse>
		<url>Isaiah 4:3</url>
		<gref>Luke 10:20</gref>
		<nref>Romans 11:4</nref>
		<nref>Romans 11:5</nref>
		<oref>Exodus 32:32</oref>
		<oref>Psalm 69:28</oref>
		<oref>Psalm 87:6</oref>
		<oref>Isaiah 28:5</oref>
		<oref>Isaiah 35:8</oref>
		<oref>Isaiah 46:3</oref>
		<oref>Isaiah 52:1</oref>
		<oref>Isaiah 62:12</oref>
		<oref>Joel 3:17</oref>
		<oref>Obadiah 1:17</oref>
		<oref>Malachi 3:16</oref>
	</verse>
	<verse>
		<url>Isaiah 4:4</url>
		<gref>Matthew 3:11</gref>
		<oref>Psalm 51:2</oref>
		<oref>Song of Solomon 3:11</oref>
		<oref>Isaiah 1:15</oref>
		<oref>Isaiah 1:31</oref>
		<oref>Isaiah 3:16</oref>
		<oref>Isaiah 9:19</oref>
		<oref>Isaiah 28:6</oref>
		<oref>Ezekiel 36:25</oref>
		<oref>Joel 3:21</oref>
		<oref>Zechariah 3:3</oref>
		<oref>Zechariah 13:1</oref>
	</verse>
	<verse>
		<url>Isaiah 4:5</url>
		<oref>Exodus 13:21</oref>
		<oref>Exodus 13:22</oref>
		<oref>Exodus 24:16</oref>
		<oref>Exodus 40:38</oref>
		<oref>Numbers 9:15</oref>
		<oref>Psalm 105:39</oref>
		<oref>Isaiah 60:1</oref>
		<oref>Isaiah 60:2</oref>
		<oref>Zechariah 2:5</oref>
	</verse>
	<verse>
		<url>Isaiah 4:6</url>
		<oref>Psalm 27:5</oref>
		<oref>Psalm 55:8</oref>
		<oref>Isaiah 8:14</oref>
		<oref>Isaiah 14:32</oref>
		<oref>Isaiah 25:4</oref>
		<oref>Isaiah 32:1</oref>
		<oref>Isaiah 32:2</oref>
	</verse>
</verses>